url_or_relative_url_field/__init__.py
url_or_relative_url_field/apps.py
url_or_relative_url_field/fields.py
url_or_relative_url_field/forms.py
url_or_relative_url_field/validators.py
django_url_or_relative_url_field-0.2.0.dist-info/LICENSE
django_url_or_relative_url_field-0.2.0.dist-info/WHEEL
django_url_or_relative_url_field-0.2.0.dist-info/METADATA
django_url_or_relative_url_field-0.2.0.dist-info/RECORD
